jinja2_lucide.py
jinja2_lucide-0.1.1.dist-info/METADATA
jinja2_lucide-0.1.1.dist-info/WHEEL
jinja2_lucide-0.1.1.dist-info/RECORD
