Metadata-Version: 2.4
Name: jinja2-lucide
Version: 0.1.1
Summary: An jinja2 tags, allows lucide-icons to be embedded as inline svg into templates. 
Author: DotLabs Team
Author-email: teams@dotlabs.dev
Requires-Python: >=3.14,<4.0
Classifier: Programming Language :: Python :: 3
Classifier: Programming Language :: Python :: 3.14
Requires-Dist: jinja2 (>=3.1.6,<4.0.0)
Requires-Dist: lucide-py (>=0.2.1,<0.3.0)
